ft_package_kyeonkim/__init__.py
ft_package_kyeonkim/countlist.py
ft_package_kyeonkim-0.0.5.dist-info/METADATA
ft_package_kyeonkim-0.0.5.dist-info/WHEEL
ft_package_kyeonkim-0.0.5.dist-info/licenses/LICENSE
ft_package_kyeonkim-0.0.5.dist-info/RECORD
