Metadata-Version: 2.1
Name: ft_package_kyeonkim
Version: 0.0.5
Summary: A small example package
Author-email: kyeonkim <kyeonkim@student.42seoul.kr>
License-File: LICENSE
Classifier: License :: OSI Approved :: MIT License
Classifier: Operating System :: OS Independent
Classifier: Programming Language :: Python :: 3
Requires-Python: >=3.10
